powl/__init__.py
powl/main.py
powl/conversion/__init__.py
powl/conversion/converter.py
powl/conversion/to_powl/__init__.py
powl/conversion/to_powl/from_tree.py
powl/conversion/to_powl/from_pn/__init__.py
powl/conversion/to_powl/from_pn/converter.py
powl/conversion/to_powl/from_pn/utils/__init__.py
powl/conversion/to_powl/from_pn/utils/cut_detection.py
powl/conversion/to_powl/from_pn/utils/preprocessing.py
powl/conversion/to_powl/from_pn/utils/subnet_creation.py
powl/conversion/to_powl/from_pn/utils/weak_reachability.py
powl/conversion/utils/__init__.py
powl/conversion/utils/pn_reduction.py
powl/conversion/variants/__init__.py
powl/conversion/variants/to_bpmn.py
powl/conversion/variants/to_bpmn_with_resources.py
powl/conversion/variants/to_petri_net.py
powl/discovery/__init__.py
powl/discovery/dfg_based/__init__.py
powl/discovery/dfg_based/algorithm.py
powl/discovery/dfg_based/utils/__init__.py
powl/discovery/dfg_based/variants/__init__.py
powl/discovery/dfg_based/variants/dfg_im_decision_graph_maximal.py
powl/discovery/dfg_based/variants/dfg_im_maximal.py
powl/discovery/dfg_based/variants/dfg_im_tree.py
powl/discovery/dfg_based/variants/im_dynamic_clustering_frequencies.py
powl/discovery/object_centric/__init__.py
powl/discovery/object_centric/algorithm.py
powl/discovery/object_centric/variants/__init__.py
powl/discovery/object_centric/variants/flattening/__init__.py
powl/discovery/object_centric/variants/flattening/miner.py
powl/discovery/object_centric/variants/oc_powl/__init__.py
powl/discovery/object_centric/variants/oc_powl/miner.py
powl/discovery/object_centric/variants/oc_powl/utils/__init__.py
powl/discovery/object_centric/variants/oc_powl/utils/divergence_free_graph.py
powl/discovery/object_centric/variants/oc_powl/utils/filtering.py
powl/discovery/object_centric/variants/oc_powl/utils/interaction_properties.py
powl/discovery/object_centric/variants/oc_powl/utils/ocpn_conversion.py
powl/discovery/object_centric/variants/oc_tree/__init__.py
powl-2.3.1.dist-info/licenses/LICENSE.txt
powl-2.3.1.dist-info/METADATA
powl-2.3.1.dist-info/WHEEL
powl-2.3.1.dist-info/top_level.txt
powl-2.3.1.dist-info/RECORD
