Metadata-Version: 2.4
Name: powl
Version: 2.3.1
Summary: POWL Miner: Process Mining with the Partially Ordered Workflow Language
Author-email: Humam Kourani <humam.kourani@fit.fraunhofer.de>
License:                     GNU AFFERO GENERAL PUBLIC LICENSE
Project-URL: Repository, https://github.com/humam-kourani/POWL
Keywords: process mining,business process management
Classifier: Development Status :: 4 - Beta
Classifier: Intended Audience :: Developers
Classifier: License :: OSI Approved :: GNU Affero General Public License v3 or later (AGPLv3+)
Classifier: Programming Language :: Python :: 3.9
Classifier: Programming Language :: Python :: 3.10
Classifier: Programming Language :: Python :: 3.11
Classifier: Programming Language :: Python :: 3.12
Classifier: Programming Language :: Python :: 3.13
Requires-Python: >=3.9
License-File: LICENSE.txt
Requires-Dist: pm4py
Requires-Dist: graphviz
Requires-Dist: rustxes
Requires-Dist: streamlit
Requires-Dist: networkx
Requires-Dist: shapely
Dynamic: license-file
